daylight_evapotranspiration/__init__.py
daylight_evapotranspiration/daylight_evapotranspiration.py
daylight_evapotranspiration/version.py
daylight_evapotranspiration-1.3.4.dist-info/licenses/LICENSE
daylight_evapotranspiration-1.3.4.dist-info/METADATA
daylight_evapotranspiration-1.3.4.dist-info/WHEEL
daylight_evapotranspiration-1.3.4.dist-info/top_level.txt
daylight_evapotranspiration-1.3.4.dist-info/RECORD
